osef/__init__.py
osef/_logger.py
osef/_version.py
osef/frame_helper/__init__.py
osef/frame_helper/exceptions.py
osef/frame_helper/field_classes.py
osef/frame_helper/frame_edition.py
osef/frame_helper/osef_frame.py
osef/packing/__init__.py
osef/packing/packer.py
osef/parsing/__init__.py
osef/parsing/_lazy_parser.py
osef/parsing/_parser.py
osef/parsing/_parser_common.py
osef/parsing/osef_stream.py
osef/parsing/parser.py
osef/parsing/scanner.py
osef/spec/__init__.py
osef/spec/_formats.py
osef/spec/_packers.py
osef/spec/_types.py
osef/spec/constants.py
osef/spec/osef_types.py
osef-3.3.2.dist-info/LICENSE
osef-3.3.2.dist-info/METADATA
osef-3.3.2.dist-info/WHEEL
osef-3.3.2.dist-info/top_level.txt
osef-3.3.2.dist-info/RECORD
