Metadata-Version: 2.1
Name: osef
Version: 3.3.2
Summary: Osef python library.
Author-email: Outsight Developpers <support@outsight.tech>
Project-URL: Documentation, https://outsight-tech.gitlab.io/common/osef-python-library/
Project-URL: Support, https://support.outsight.ai
Project-URL: Changes, https://outsight-tech.gitlab.io/common/osef-python-library/CHANGELOG.html
Classifier: Programming Language :: Python :: 3
Classifier: License :: OSI Approved :: MIT License
Classifier: Operating System :: OS Independent
Requires-Python: >=3.8
License-File: LICENSE
Requires-Dist: numpy>=1.21.0
